Board/__init__.py
Board/board.py
Compiler/__init__.py
Compiler/compiler.py
Robot/__init__.py
Robot/robot.py
Simulator/__init__.py
Simulator/simulator.py
Simulator/utilities.py
robotchallenge-1.0.1.dist-info/LICENSE
robotchallenge-1.0.1.dist-info/METADATA
robotchallenge-1.0.1.dist-info/WHEEL
robotchallenge-1.0.1.dist-info/top_level.txt
robotchallenge-1.0.1.dist-info/RECORD
