Metadata-Version: 2.1
Name: robotchallenge
Version: 1.0.1
Summary: An Attempt At Robot Challenge
Home-page: https://github.com/sheecegardezi/RobotChallenge
Author: Sheece Gardezi
Author-email: sheecegardezi@gmail.com
License: Apache 2.0
Keywords: robot challenge
Platform: UNKNOWN
Classifier: Programming Language :: Python :: 3
Classifier: Programming Language :: Python :: 3 :: Only
Classifier: Programming Language :: Python :: 3.7
Classifier: Programming Language :: Python :: 3.8
Classifier: Programming Language :: Python :: 3.9
Classifier: Programming Language :: Python :: 3.10
Classifier: Programming Language :: Python :: Implementation :: PyPy
Classifier: Operating System :: OS Independent
Requires-Python: >=3.7
License-File: LICENSE
Requires-Dist: pytest
